Metadata-Version: 1.0
Name: similardata
Version: 0.0.2
Summary: similardata
Home-page: https://github.com/anisha22678/similardata
Author: UNKNOWN
Author-email: UNKNOWN
License: UNKNOWN
Platform: UNKNOWN
